news_crawler_vpt/__init__.py
news_crawler_vpt/category_crawler.py
news_crawler_vpt/data.csv
news_crawler_vpt/data.json
news_crawler_vpt/data_ex.py
news_crawler_vpt/kategorijos.csv
news_crawler_vpt/main.py
news_crawler_vpt-1.0.dist-info/METADATA
news_crawler_vpt-1.0.dist-info/WHEEL
news_crawler_vpt-1.0.dist-info/RECORD
