Metadata-Version: 2.1
Name: news-crawler_vpt
Version: 1.0
Summary: 
Author: Vilmantas
Author-email: alchemikaslt1@gmail.com
Requires-Python: >=3.11,<4.0
Classifier: Programming Language :: Python :: 3
Classifier: Programming Language :: Python :: 3.11
Classifier: Programming Language :: Python :: 3.12
Requires-Dist: chromedrivermanager (>=0.0.1,<0.0.2)
Requires-Dist: lxml (>=5.0.1,<6.0.0)
Requires-Dist: selenium (>=4.16.0,<5.0.0)
Requires-Dist: webdriver-manager (>=4.0.1,<5.0.0)
